LICENSE
MANIFEST.in
README.md
setup.py
diso/__init__.py
diso.egg-info/PKG-INFO
diso.egg-info/SOURCES.txt
diso.egg-info/dependency_links.txt
diso.egg-info/not-zip-safe
diso.egg-info/requires.txt
diso.egg-info/top_level.txt
src/cudualmc.cu
src/cudualmc.h
src/cumc.cu
src/cumc.h
src/pybind.cpp